simple_file_lock/__init__.py
simple_file_lock/version.py
simple_file_lock-2024.1.dist-info/METADATA
simple_file_lock-2024.1.dist-info/WHEEL
simple_file_lock-2024.1.dist-info/licenses/LICENSE.txt
simple_file_lock-2024.1.dist-info/RECORD
