Metadata-Version: 2.1
Name: simple_file_lock
Version: 2024.1
Summary: Context manager for simple file locking.
Project-URL: Homepage, https://gitlab.inria.fr/jrye/simple-file-lock
Project-URL: Source, https://gitlab.inria.fr/jrye/simple-file-lock.git
Project-URL: Documentation, https://jrye.gitlabpages.inria.fr/simple-file-lock
Project-URL: Issues, https://gitlab.inria.fr/jrye/simple-file-lock/-/issues
Author-email: Jan-Michael Rye <jan-michael.rye@inria.fr>
License: MIT License
License-File: LICENSE.txt
Classifier: License :: OSI Approved :: MIT License
Classifier: Operating System :: OS Independent
Classifier: Programming Language :: Python :: 3
Requires-Python: >=3.7
Requires-Dist: psutil
